RAPDOR/__init__.py
RAPDOR/_version.py
RAPDOR/dashConfig.yaml
RAPDOR/datastructures.py
RAPDOR/executables.py
RAPDOR/plots.py
RAPDOR/tests/test_dash.py
RAPDOR/tests/test_datastructures.py
RAPDOR/tests/testData/testDesign.tsv
RAPDOR/tests/testData/testFile.tsv
RAPDOR/tests/testData/tutorialData.tsv
RAPDOR/tests/testData/tutorialDesign.tsv
RAPDOR/visualize/__init__.py
RAPDOR/visualize/appDefinition.py
RAPDOR/visualize/backends.py
RAPDOR/visualize/clusterAndSettings.py
RAPDOR/visualize/colorSelection.py
RAPDOR/visualize/dataBackEnd.py
RAPDOR/visualize/dataTable.py
RAPDOR/visualize/distributionAndHeatmap.py
RAPDOR/visualize/modals.py
RAPDOR/visualize/runApp.py
RAPDOR/visualize/staticContent.py
RAPDOR/visualize/assets/01_style.css
RAPDOR/visualize/assets/Icon.svg
RAPDOR/visualize/assets/RAPDOR.svg
RAPDOR/visualize/assets/RAPDORRaptor.svg
RAPDOR/visualize/assets/RAPDOR_light.svg
RAPDOR/visualize/assets/RAPDOR_light_with_text.svg
RAPDOR/visualize/assets/RAPDOR_with_text.svg
RAPDOR/visualize/assets/additional.js
RAPDOR/visualize/assets/defaultWelcome.md
RAPDOR/visualize/assets/favicon.ico
RAPDOR/visualize/assets/index.html
RAPDOR/visualize/assets/tutorial.json
RAPDOR/visualize/assets/tutorialDisplayMode.json
RAPDOR/visualize/callbacks/__init__.py
RAPDOR/visualize/callbacks/colorCallbacks.py
RAPDOR/visualize/callbacks/mainCallbacks.py
RAPDOR/visualize/callbacks/modalCallbacks.py
RAPDOR/visualize/callbacks/plotCallbacks.py
RAPDOR/visualize/callbacks/tableCallbacks.py
RAPDOR/visualize/pages/__init__.py
RAPDOR/visualize/pages/analysis_page.py
RAPDOR/visualize/pages/figure_factory.py
RAPDOR/visualize/pages/upload_page.py
RAPDOR/visualize/pages/welcome.py
rapdor-0.1.10.data/scripts/executables.py
rapdor-0.1.10.data/scripts/versioneer.py
rapdor-0.1.10.dist-info/licenses/LICENSE
rapdor-0.1.10.dist-info/METADATA
rapdor-0.1.10.dist-info/WHEEL
rapdor-0.1.10.dist-info/entry_points.txt
rapdor-0.1.10.dist-info/top_level.txt
rapdor-0.1.10.dist-info/RECORD
