Metadata-Version: 2.4
Name: RAPDOR
Version: 0.1.10
Summary: Package for identification of RNA dependent Proteins from mass spec data 
Home-page: https://github.com/domonik/RAPDOR
Author: domonik
Author-email: dominik.rabsch@gmail.com
License: LICENSE
License-File: LICENSE
Requires-Dist: statsmodels
Requires-Dist: numpy
Requires-Dist: scipy<1.16
Requires-Dist: plotly>=5.16
Requires-Dist: pandas
Requires-Dist: dash>=2.5
Requires-Dist: dash_bootstrap_components
Requires-Dist: scikit-learn
Requires-Dist: kaleido
Requires-Dist: dash_daq
Requires-Dist: dash_extensions
Requires-Dist: pyYAML
Requires-Dist: dash[diskcache]
Dynamic: author
Dynamic: author-email
Dynamic: description
Dynamic: description-content-type
Dynamic: home-page
Dynamic: license
Dynamic: license-file
Dynamic: requires-dist
Dynamic: summary
